vsg/CustomArgumentParser.py
vsg/__init__.py
vsg/__main__.py
vsg/__parser__.py
vsg/__rule_doc_gen__.py
vsg/apply_rules.py
vsg/block_rule.py
vsg/cmd_line_args.py
vsg/config.py
vsg/deprecated_rule.py
vsg/exceptions.py
vsg/junit.py
vsg/parser.py
vsg/prerequisite.py
vsg/proposed_rule.py
vsg/rule.py
vsg/rule_list.py
vsg/severity.py
vsg/token_map.py
vsg/tokens.py
vsg/utils.py
vsg/version.py
vsg/violation.py
vsg/interfaces/__init__.py
vsg/interfaces/notepad_pp.py
vsg/report/__init__.py
vsg/report/quality_report.py
vsg/report/summary_stdout.py
vsg/report/syntastic_stdout.py
vsg/report/vsg_stdout.py
vsg/rule_group/__init__.py
vsg/rule_group/alignment.py
vsg/rule_group/blank_line.py
vsg/rule_group/case.py
vsg/rule_group/indent.py
vsg/rule_group/length.py
vsg/rule_group/naming.py
vsg/rule_group/structure.py
vsg/rule_group/whitespace.py
vsg/rules/__init__.py
vsg/rules/align_consecutive_lines_after_line_starting_with_token_and_stopping_with_token.py
vsg/rules/align_consecutive_lines_starting_with_a_comment_above_line_starting_with_token.py
vsg/rules/align_left_token_with_right_token_if_right_token_starts_a_line.py
vsg/rules/align_tokens_in_region_between_tokens.py
vsg/rules/align_tokens_in_region_between_tokens_skipping_lines_starting_with_tokens.py
vsg/rules/align_tokens_in_region_between_tokens_unless_between_tokens.py
vsg/rules/align_tokens_in_region_between_tokens_when_between_tokens_unless_between_tokens.py
vsg/rules/alignment_utils.py
vsg/rules/analysis.py
vsg/rules/blank_line_above_line_starting_with_token.py
vsg/rules/blank_line_above_line_starting_with_token_when_between_tokens.py
vsg/rules/blank_line_below_line_ending_with_several_possible_tokens.py
vsg/rules/blank_line_below_line_ending_with_token.py
vsg/rules/blank_lines_between_token_pairs.py
vsg/rules/case_utils.py
vsg/rules/check.py
vsg/rules/consistent_case_utils.py
vsg/rules/consistent_interface_token_case.py
vsg/rules/consistent_subprogram_parameter_token_case.py
vsg/rules/consistent_token_case.py
vsg-3.35.0.dist-info/LICENSE
vsg-3.35.0.dist-info/METADATA
vsg-3.35.0.dist-info/WHEEL
vsg-3.35.0.dist-info/entry_points.txt
vsg-3.35.0.dist-info/top_level.txt
vsg-3.35.0.dist-info/RECORD
