Metadata-Version: 2.1
Name: vsg
Version: 3.35.0
Summary: VHDL Style Guide
Author-email: Jeremiah C Leary <jeremiah.c.leary@gmail.com>
Project-URL: Homepage, https://github.com/jeremiah-c-leary/vhdl-style-guide
Project-URL: Download, https://github.com/jeremiah-c-leary/vhdl-style-guide
Keywords: beautify,guide,lint,style,vhdl
Classifier: Development Status :: 4 - Beta
Classifier: Environment :: Console
Classifier: Intended Audience :: End Users/Desktop
Classifier: License :: OSI Approved :: GNU General Public License v3 (GPLv3)
Classifier: Natural Language :: English
Classifier: Operating System :: POSIX :: Linux
Classifier: Programming Language :: Python :: 3
Classifier: Topic :: Software Development :: Quality Assurance
Classifier: Topic :: Text Processing :: General
Requires-Python: >=3.8
License-File: LICENSE
Requires-Dist: PyYAML>=5.1
Provides-Extra: dev
Requires-Dist: pre-commit>=3.2.0; extra == "dev"
Requires-Dist: pylint; extra == "dev"
Requires-Dist: wheel; extra == "dev"
Provides-Extra: docs
Requires-Dist: docutils; extra == "docs"
Requires-Dist: readthedocs-sphinx-search; extra == "docs"
Requires-Dist: sphinx; extra == "docs"
Requires-Dist: sphinx-rtd-theme; extra == "docs"
Provides-Extra: tests
Requires-Dist: pytest; extra == "tests"
Requires-Dist: pytest-cov; extra == "tests"
Requires-Dist: pytest-html; extra == "tests"
Requires-Dist: pytest-html-reporter; extra == "tests"
Requires-Dist: pytest-xdist[psutil]; extra == "tests"
